pythoncfs-0.1.2.dist-info/RECORD
pythoncfs-0.1.2.dist-info/WHEEL
pythoncfs-0.1.2.dist-info/METADATA
pythoncfs-0.1.2.dist-info/licenses/LICENSE.txt
CFS/_routines.cpython-313-x86_64-linux-gnu.so
CFS/_constants.cpython-313-x86_64-linux-gnu.so
CFS/CFSFile.cpython-313-x86_64-linux-gnu.so
