Metadata-Version: 2.1
Name: pythonCFS
Version: 0.1.2
Summary: Python wrapper for the Cambridge Electronic Design CFS library.
Author-Email: Seamus <<m0ose01@proton.me>>
License: MIT License
Classifier: Intended Audience :: Science/Research
Classifier: Programming Language :: C
Classifier: Programming Language :: Cython
Classifier: Programming Language :: Python
Classifier: License :: OSI Approved :: MIT License
Requires-Python: >=3.10
Provides-Extra: dev
Requires-Dist: pytest>=8.3.2; extra == "dev"
Requires-Dist: build>=1.2.1; extra == "dev"
